LICENSE
MANIFEST.in
README.md
setup.py
chembl_webservices/__init__.py
chembl_webservices/dis.py
chembl_webservices/middleware.py
chembl_webservices/models.py
chembl_webservices/search_indexes.py
chembl_webservices/tests.py
chembl_webservices/urls.py
chembl_webservices.egg-info/PKG-INFO
chembl_webservices.egg-info/SOURCES.txt
chembl_webservices.egg-info/dependency_links.txt
chembl_webservices.egg-info/not-zip-safe
chembl_webservices.egg-info/requires.txt
chembl_webservices.egg-info/top_level.txt
chembl_webservices/core/__init__.py
chembl_webservices/core/api.py
chembl_webservices/core/fields.py
chembl_webservices/core/meta.py
chembl_webservices/core/pagination.py
chembl_webservices/core/resource.py
chembl_webservices/core/serialization.py
chembl_webservices/core/utils.py
chembl_webservices/management/__init__.py
chembl_webservices/management/commands/__init__.py
chembl_webservices/management/commands/rebuild_chembl_index.py
chembl_webservices/management/commands/update_chembl_index.py
chembl_webservices/resources/__init__.py
chembl_webservices/resources/activities.py
chembl_webservices/resources/assays.py
chembl_webservices/resources/atc.py
chembl_webservices/resources/binding_site.py
chembl_webservices/resources/bio_component.py
chembl_webservices/resources/cell_line.py
chembl_webservices/resources/chembl_id.py
chembl_webservices/resources/compound_record.py
chembl_webservices/resources/docs.py
chembl_webservices/resources/document_similarity.py
chembl_webservices/resources/document_terms.py
chembl_webservices/resources/drug.py
chembl_webservices/resources/go_slim.py
chembl_webservices/resources/image.py
chembl_webservices/resources/indication.py
chembl_webservices/resources/mechanism.py
chembl_webservices/resources/metabolism.py
chembl_webservices/resources/molecule.py
chembl_webservices/resources/molecule_forms.py
chembl_webservices/resources/organism.py
chembl_webservices/resources/protein_class.py
chembl_webservices/resources/similarity.py
chembl_webservices/resources/source.py
chembl_webservices/resources/status.py
chembl_webservices/resources/structural_alerts.py
chembl_webservices/resources/substructure.py
chembl_webservices/resources/target.py
chembl_webservices/resources/target_components.py
