Metadata-Version: 1.1
Name: chembl-webservices
Version: 2.7.3
Summary: Python package providing chembl web services API.
Home-page: https://www.ebi.ac.uk/chembldb/index.php/ws
Author: Michal Nowotka
Author-email: mnowotka@ebi.ac.uk
License: Apache Software License
Platform: UNKNOWN
Classifier: Development Status :: 3 - Alpha
Classifier: Environment :: Web Environment
Classifier: Framework :: Django
Classifier: Intended Audience :: Developers
Classifier: License :: OSI Approved :: Apache Software License
Classifier: Operating System :: POSIX :: Linux
Classifier: Programming Language :: Python :: 2.7
Classifier: Topic :: Scientific/Engineering :: Chemistry
